pdr/__init__.py
pdr/_scaling.py
pdr/bit_handling.py
pdr/browsify.py
pdr/datatypes.py
pdr/errors.py
pdr/func.py
pdr/np_utils.py
pdr/pd_utils.py
pdr/pdr.py
pdr/pdrtypes.py
pdr/pil_utils.py
pdr/pvl_utils.py
pdr/utils.py
pdr/formats/__init__.py
pdr/formats/cassini.py
pdr/formats/checkers.py
pdr/formats/clementine.py
pdr/formats/dawn.py
pdr/formats/diviner.py
pdr/formats/epoxi.py
pdr/formats/galileo.py
pdr/formats/ground.py
pdr/formats/ihw.py
pdr/formats/iue.py
pdr/formats/juno.py
pdr/formats/lp.py
pdr/formats/lro.py
pdr/formats/lroc.py
pdr/formats/mariner.py
pdr/formats/mer.py
pdr/formats/mex.py
pdr/formats/mgn.py
pdr/formats/mgs.py
pdr/formats/mro.py
pdr/formats/msl_apxs.py
pdr/formats/msl_ccam.py
pdr/formats/msl_cmn.py
pdr/formats/msl_places.py
pdr/formats/msl_rems.py
pdr/formats/msx.py
pdr/formats/nh.py
pdr/formats/odyssey.py
pdr/formats/phoenix.py
pdr/formats/pvo.py
pdr/formats/rosetta.py
pdr/formats/saturn_rpx.py
pdr/formats/themis.py
pdr/formats/ulysses.py
pdr/formats/vega.py
pdr/formats/viking.py
pdr/formats/voyager.py
pdr/loaders/__init__.py
pdr/loaders/_helpers.py
pdr/loaders/astrowrap.py
pdr/loaders/datawrap.py
pdr/loaders/dispatch.py
pdr/loaders/handlers.py
pdr/loaders/image.py
pdr/loaders/queries.py
pdr/loaders/table.py
pdr/loaders/text.py
pdr/loaders/utility.py
pdr/parselabel/__init__.py
pdr/parselabel/pds3.py
pdr/parselabel/pds4.py
pdr/parselabel/utils.py
pdr/pds4_tools/CREDITS
pdr/pds4_tools/LICENSES
pdr/pds4_tools/__about__.py
pdr/pds4_tools/__init__.py
pdr/pds4_tools/extern/__init__.py
pdr/pds4_tools/extern/appdirs.py
pdr/pds4_tools/extern/argparse.py
pdr/pds4_tools/extern/cached_property.py
pdr/pds4_tools/extern/ordered_dict.py
pdr/pds4_tools/extern/six.py
pdr/pds4_tools/extern/zscale.py
pdr/pds4_tools/reader/__init__.py
pdr/pds4_tools/reader/array_objects.py
pdr/pds4_tools/reader/core.py
pdr/pds4_tools/reader/data.py
pdr/pds4_tools/reader/data_types.py
pdr/pds4_tools/reader/general_objects.py
pdr/pds4_tools/reader/header_objects.py
pdr-1.4.0.dist-info/LICENSE.md
pdr-1.4.0.dist-info/METADATA
pdr-1.4.0.dist-info/WHEEL
pdr-1.4.0.dist-info/top_level.txt
pdr-1.4.0.dist-info/RECORD
