Metadata-Version: 2.2
Name: pdr
Version: 1.4.0
Summary: Planetary Data Reader
Author-email: Chase Million <chase@millionconcepts.com>, "Michael St. Clair" <mstclair@millionconcepts.com>, Sierra Brown <sierra@millionconcepts.com>, Sabrina Curtis <scurtis@millionconcepts.com>, Zack Weinberg <zack@millionconcepts.com>
License: ###  BSD 3-Clause License
Project-URL: Repository, https://github.com/MillionConcepts/pdr
Classifier: Development Status :: 4 - Beta
Classifier: License :: OSI Approved :: BSD License
Classifier: Operating System :: OS Independent
Classifier: Programming Language :: Python :: 3
Requires-Python: >=3.9
License-File: LICENSE.md
Requires-Dist: dustgoggles
Requires-Dist: more_itertools
Requires-Dist: multidict
Requires-Dist: numpy
Requires-Dist: pandas>=2.0.0
Requires-Dist: rms-vax
Provides-Extra: pillow
Requires-Dist: pillow; extra == "pillow"
Provides-Extra: fits
Requires-Dist: astropy; extra == "fits"
Provides-Extra: notebooks
Requires-Dist: jupyter; extra == "notebooks"
Provides-Extra: pvl
Requires-Dist: pvl; extra == "pvl"
Provides-Extra: tests
Requires-Dist: pytest; extra == "tests"
Provides-Extra: fuzzy
Requires-Dist: Levenshtein; extra == "fuzzy"
